{
	"flowBizlogic":{
		"nodeDataArray":[
			{
				"loc":"-100 -180",
				"groupId":"FLOW",
				"actionId":"startAction",
				"refClass":"com.leise.flow.action.flow.StartAction",
				"text":"开始",
				"category":"FLOW_START",
				"key":-1,
				"actionName":"开始"
			},
			{
				"loc":"-100 220",
				"groupId":"FLOW",
				"actionId":"endAction",
				"refClass":"com.leise.flow.action.flow.EndAction",
				"text":"结束",
				"category":"FLOW_END",
				"key":-2,
				"actionName":"结束"
			},
			{
				"loc":"-100 10",
				"newTransation":"false",
				"operSql":"delete from flow_data where flow_info_id =:flowInfoId",
				"groupId":"DATABASE",
				"actionId":"singleOperAction",
				"refClass":"com.leise.flow.action.database.SingleOperAction",
				"text":"单笔操作",
				"category":"DATABASE",
				"key":-4,
				"actionName":"单笔操作"
			},
			{
				"loc":"-100 -90",
				"newTransation":"false",
				"operSql":"delete from flow_info where id = :flowInfoId",
				"groupId":"DATABASE",
				"actionId":"singleOperAction",
				"refClass":"com.leise.flow.action.database.SingleOperAction",
				"text":"单笔操作",
				"category":"DATABASE",
				"key":-6,
				"actionName":"单笔操作"
			},
			{
				"loc":"-100 130",
				"newTransation":"false",
				"operSql":"delete from flow_bizlogic where flow_info_id = :flowInfoId",
				"groupId":"DATABASE",
				"actionId":"singleOperAction",
				"refClass":"com.leise.flow.action.database.SingleOperAction",
				"text":"单笔操作",
				"category":"DATABASE",
				"key":-5,
				"actionName":"单笔操作"
			}
		],
		"linkDataArray":[
			{
				"from":-1,
				"to":-6,
				"points":[
					-100,
					-158.18217008058414,
					-100,
					-148.18217008058414,
					-100,
					-134.09108504029206,
					-100,
					-134.09108504029206,
					-100,
					-120,
					-100,
					-110
				]
			},
			{
				"from":-6,
				"to":-4,
				"points":[
					-100,
					-70,
					-100,
					-60,
					-100,
					-40,
					-100,
					-40,
					-100,
					-20,
					-100,
					-10
				]
			},
			{
				"from":-4,
				"to":-5,
				"points":[
					-100,
					30,
					-100,
					40,
					-100,
					70,
					-100,
					70,
					-100,
					100,
					-100,
					110
				]
			},
			{
				"from":-5,
				"to":-2,
				"points":[
					-100,
					150,
					-100,
					160,
					-100,
					174.09108504029206,
					-100,
					174.09108504029206,
					-100,
					188.18217008058414,
					-100,
					198.18217008058414
				]
			}
		]
	},
	"flowData":[
		{
			"collectFlag":false,
			"dataCode":"flowInfoId",
			"dataName":"流程ID",
			"flowInfoId":100011,
			"inputFlag":true,
			"outputFlag":false,
			"validStatus":false
		}
	],
	"flowInfo":{
		"flowId":"deleteFlowInfo",
		"flowName":"流程信息单笔删除",
		"flowVersion":"1.0.0",
		"moduleId":"leise-provider-flow",
		"requestUrl":"/design/deleteFlowInfo/1.0.0",
		"status":"UNKNOW",
		"validStatus":true
	},
	"version":"6f8198af1d9c516580527f8129c91a22"
}